CHANGELOG.md
LICENSE
MANIFEST.in
README.md
pyproject.toml
requirements-dev.txt
requirements.txt
setup.py
cooltools/__init__.py
cooltools/__main__.py
cooltools.egg-info/PKG-INFO
cooltools.egg-info/SOURCES.txt
cooltools.egg-info/dependency_links.txt
cooltools.egg-info/entry_points.txt
cooltools.egg-info/not-zip-safe
cooltools.egg-info/requires.txt
cooltools.egg-info/top_level.txt
cooltools/api/__init__.py
cooltools/api/coverage.py
cooltools/api/directionality.py
cooltools/api/dotfinder.py
cooltools/api/eigdecomp.py
cooltools/api/expected.py
cooltools/api/insulation.py
cooltools/api/rearrange.py
cooltools/api/saddle.py
cooltools/api/sample.py
cooltools/api/snipping.py
cooltools/api/virtual4c.py
cooltools/cli/__init__.py
cooltools/cli/coverage.py
cooltools/cli/dots.py
cooltools/cli/eigs_cis.py
cooltools/cli/eigs_trans.py
cooltools/cli/expected_cis.py
cooltools/cli/expected_trans.py
cooltools/cli/genome.py
cooltools/cli/insulation.py
cooltools/cli/logbin_expected.py
cooltools/cli/pileup.py
cooltools/cli/rearrange.py
cooltools/cli/saddle.py
cooltools/cli/sample.py
cooltools/cli/util.py
cooltools/cli/virtual4c.py
cooltools/lib/__init__.py
cooltools/lib/_numutils.c
cooltools/lib/_numutils.pyx
cooltools/lib/_query.py
cooltools/lib/checks.py
cooltools/lib/common.py
cooltools/lib/io.py
cooltools/lib/numutils.py
cooltools/lib/peaks.py
cooltools/lib/plotting.py
cooltools/lib/runlength.py
cooltools/lib/schemas.py
cooltools/sandbox/__init__.py
cooltools/sandbox/balance.py
cooltools/sandbox/contrast.py
cooltools/sandbox/cool2cworld.py
cooltools/sandbox/cross_score.py
cooltools/sandbox/expected_smoothing.py
cooltools/sandbox/obs_over_exp_cooler.py
cooltools/sandbox/pairs_scaling_functions.py
docs/Makefile
docs/cli.rst
docs/conf.py
docs/cooltools.lib.rst
docs/cooltools.rst
docs/index.rst
docs/make.bat
docs/releases.md
docs/requirements.txt
docs/figs/cooltools-logo-futura.png
docs/notebooks_old/01_scaling-curves.ipynb
docs/notebooks_old/02_expected.ipynb
docs/notebooks_old/03_eigendecomposition.ipynb
docs/notebooks_old/04_saddle-plots.ipynb
docs/notebooks_old/05_insulation-score.ipynb
docs/notebooks_old/06_snipping-pileups.ipynb
docs/notebooks_old/07_pileups2.ipynb
