Metadata-Version: 2.1
Name: cooltools
Version: 0.7.0
Summary: Analysis tools for genomic interaction data stored in .cool format
Home-page: https://github.com/open2c/cooltools
Author: Open2C
Author-email: open.chromosome.collective@gmail.com
License: MIT
Keywords: genomics,bioinformatics,Hi-C,analysis,cooler
Classifier: Development Status :: 4 - Beta
Classifier: Programming Language :: Python
Classifier: Programming Language :: Python :: 3
Classifier: Programming Language :: Python :: 3.8
Classifier: Programming Language :: Python :: 3.9
Classifier: Programming Language :: Python :: 3.10
Requires-Python: >=3.7.1
License-File: LICENSE
Requires-Dist: bioframe>=0.4.1
Requires-Dist: click>=7
Requires-Dist: cooler>=0.9.1
Requires-Dist: cython
Requires-Dist: joblib
Requires-Dist: matplotlib
Requires-Dist: multiprocess
Requires-Dist: numba
Requires-Dist: numpy
Requires-Dist: pandas>=1.5.1
Requires-Dist: scikit-learn>=1.1.2
Requires-Dist: scipy
Requires-Dist: scikit-image
